kurrentclient/__init__.py
kurrentclient/asyncio_client.py
kurrentclient/client.py
kurrentclient/common.py
kurrentclient/connection.py
kurrentclient/connection_spec.py
kurrentclient/events.py
kurrentclient/exceptions.py
kurrentclient/gossip.py
kurrentclient/instrumentation/__init__.py
kurrentclient/instrumentation/opentelemetry/__init__.py
kurrentclient/instrumentation/opentelemetry/attributes.py
kurrentclient/instrumentation/opentelemetry/grpc.py
kurrentclient/instrumentation/opentelemetry/package.py
kurrentclient/instrumentation/opentelemetry/spanners.py
kurrentclient/instrumentation/opentelemetry/utils.py
kurrentclient/instrumentation/opentelemetry/version.py
kurrentclient/persistent.py
kurrentclient/projections.py
kurrentclient/protos/Grpc/cluster_pb2.py
kurrentclient/protos/Grpc/cluster_pb2.pyi
kurrentclient/protos/Grpc/cluster_pb2_grpc.py
kurrentclient/protos/Grpc/code_pb2.py
kurrentclient/protos/Grpc/code_pb2.pyi
kurrentclient/protos/Grpc/code_pb2_grpc.py
kurrentclient/protos/Grpc/gossip_pb2.py
kurrentclient/protos/Grpc/gossip_pb2.pyi
kurrentclient/protos/Grpc/gossip_pb2_grpc.py
kurrentclient/protos/Grpc/persistent_pb2.py
kurrentclient/protos/Grpc/persistent_pb2.pyi
kurrentclient/protos/Grpc/persistent_pb2_grpc.py
kurrentclient/protos/Grpc/projections_pb2.py
kurrentclient/protos/Grpc/projections_pb2.pyi
kurrentclient/protos/Grpc/projections_pb2_grpc.py
kurrentclient/protos/Grpc/shared_pb2.py
kurrentclient/protos/Grpc/shared_pb2.pyi
kurrentclient/protos/Grpc/shared_pb2_grpc.py
kurrentclient/protos/Grpc/status_pb2.py
kurrentclient/protos/Grpc/status_pb2.pyi
kurrentclient/protos/Grpc/status_pb2_grpc.py
kurrentclient/protos/Grpc/streams_pb2.py
kurrentclient/protos/Grpc/streams_pb2.pyi
kurrentclient/protos/Grpc/streams_pb2_grpc.py
kurrentclient/py.typed
kurrentclient/streams.py
kurrentclient-0.2.dist-info/LICENSE
kurrentclient-0.2.dist-info/METADATA
kurrentclient-0.2.dist-info/WHEEL
kurrentclient-0.2.dist-info/RECORD
