Metadata-Version: 2.1
Name: kurrentclient
Version: 0.2
Summary: Python gRPC Client for KurrentDB
Home-page: https://github.com/pyeventsourcing/esdbclient
License: BSD 3-Clause
Author: John Bywater
Author-email: john.bywater@appropriatesoftware.net
Requires-Python: >=3.8,<4.0
Classifier: Development Status :: 3 - Alpha
Classifier: License :: OSI Approved :: BSD License
Classifier: License :: Other/Proprietary License
Classifier: Programming Language :: Python
Classifier: Programming Language :: Python :: 3
Classifier: Programming Language :: Python :: 3.8
Classifier: Programming Language :: Python :: 3.9
Classifier: Programming Language :: Python :: 3.10
Classifier: Programming Language :: Python :: 3.11
Classifier: Programming Language :: Python :: 3.12
Classifier: Programming Language :: Python :: 3.13
Provides-Extra: opentelemetry
Requires-Dist: grpcio (>=1.51.0,!=1.52.*,<1.69)
Requires-Dist: opentelemetry-api (>=1.28.0,<2.0.0) ; extra == "opentelemetry"
Requires-Dist: opentelemetry-instrumentation (>=0.49b0,<0.50) ; extra == "opentelemetry"
Requires-Dist: opentelemetry-semantic-conventions (>=0.49b0,<0.50) ; extra == "opentelemetry"
Requires-Dist: protobuf (>=3.11.0)
Requires-Dist: typing_extensions
Project-URL: Repository, https://github.com/pyeventsourcing/esdbclient
